autostartx/__init__.py
autostartx/cli.py
autostartx/config.py
autostartx/daemon.py
autostartx/interactive.py
autostartx/logger.py
autostartx/models.py
autostartx/monitor.py
autostartx/process_manager.py
autostartx/service_manager.py
autostartx/storage.py
autostartx-1.0.7.dist-info/licenses/LICENSE
autostartx-1.0.7.dist-info/METADATA
autostartx-1.0.7.dist-info/WHEEL
autostartx-1.0.7.dist-info/entry_points.txt
autostartx-1.0.7.dist-info/top_level.txt
autostartx-1.0.7.dist-info/RECORD
